projected_earnings/creds.json
projected_earnings/poetry.lock
projected_earnings/run.py
projected_earnings-0.1.1.dist-info/WHEEL
projected_earnings-0.1.1.dist-info/METADATA
projected_earnings-0.1.1.dist-info/RECORD
