Metadata-Version: 2.1
Name: projected-earnings
Version: 0.1.1
Summary: Automate emails
Author: DChambers95
Author-email: dichambers95@gmail.com
Requires-Python: >=3.9,<4.0
Classifier: Programming Language :: Python :: 3
Classifier: Programming Language :: Python :: 3.9
Requires-Dist: gspread (>=3.7.0,<4.0.0)
Requires-Dist: matplotlib (>=3.3.4,<4.0.0)
Requires-Dist: oauth2client (>=4.1.3,<5.0.0)
Requires-Dist: pandas (>=1.2.3,<2.0.0)
Requires-Dist: seaborn (>=0.11.1,<0.12.0)
